teleduck/__init__.py
teleduck/__main__.py
teleduck/server.py
teleduck/certs/server.crt
teleduck/certs/server.key
teleduck-0.1.1.dist-info/METADATA
teleduck-0.1.1.dist-info/WHEEL
teleduck-0.1.1.dist-info/entry_points.txt
teleduck-0.1.1.dist-info/top_level.txt
teleduck-0.1.1.dist-info/RECORD
