Metadata-Version: 2.4
Name: teleduck
Version: 0.1.1
Summary: Serve DuckDB over PostgreSQL protocol using riffq
Requires-Python: >=3.8
Requires-Dist: duckdb
Requires-Dist: pyarrow
Requires-Dist: click
Requires-Dist: riffq
